stomp/__init__.py
stomp/__main__.py
stomp/adapter/__init__.py
stomp/adapter/multicast.py
stomp/adapter/ws.py
stomp/colours.py
stomp/connect.py
stomp/constants.py
stomp/exception.py
stomp/listener.py
stomp/logging.py
stomp/protocol.py
stomp/transport.py
stomp/utils.py
stomp_py-8.1.1.dist-info/LICENSE
stomp_py-8.1.1.dist-info/METADATA
stomp_py-8.1.1.dist-info/WHEEL
stomp_py-8.1.1.dist-info/entry_points.txt
stomp_py-8.1.1.dist-info/RECORD
