Metadata-Version: 2.1
Name: stomp-py
Version: 8.1.1
Summary: Python STOMP client, supporting versions 1.0, 1.1 and 1.2 of the protocol
Home-page: https://github.com/jasonrbriggs/stomp.py
License: Apache-2.0
Keywords: stomp,messaging,events,client
Author: Jason R Briggs
Author-email: jasonrbriggs@gmail.com
Requires-Python: >=3.7,<4.0
Classifier: Development Status :: 5 - Production/Stable
Classifier: Intended Audience :: Developers
Classifier: License :: OSI Approved :: Apache Software License
Classifier: Programming Language :: Python :: 3
Classifier: Programming Language :: Python :: 3.7
Classifier: Programming Language :: Python :: 3.8
Classifier: Programming Language :: Python :: 3.9
Classifier: Programming Language :: Python :: 3.10
Classifier: Programming Language :: Python :: 3.11
Requires-Dist: docopt (>=0.6.2,<0.7.0)
Requires-Dist: websocket-client (>=1.2.3,<2.0.0)
Project-URL: Documentation, http://jasonrbriggs.github.io/stomp.py/
Project-URL: Repository, https://github.com/jasonrbriggs/stomp.py
